CHANGES.txt
README.txt
development.ini
setup.cfg
setup.py
uploader.py
zopyx_gridfs/__init__.py
zopyx_gridfs/configure.zcml
zopyx_gridfs/resources.py
zopyx_gridfs/tests.py
zopyx_gridfs/views.py
zopyx_gridfs.egg-info/PKG-INFO
zopyx_gridfs.egg-info/SOURCES.txt
zopyx_gridfs.egg-info/dependency_links.txt
zopyx_gridfs.egg-info/entry_points.txt
zopyx_gridfs.egg-info/not-zip-safe
zopyx_gridfs.egg-info/paster_plugins.txt
zopyx_gridfs.egg-info/requires.txt
zopyx_gridfs.egg-info/top_level.txt
zopyx_gridfs/static/favicon.ico
zopyx_gridfs/static/logo.png
zopyx_gridfs/static/pylons.css
zopyx_gridfs/templates/mytemplate.pt
zopyx_gridfs/templates/upload.pt