Metadata-Version: 1.0
Name: zopyx-gridfs
Version: 0.3.0
Summary: A MongoDB-to-Web gateway based on the Pyramid web framework
Home-page: http://pypi.python.org/pypi/zopyx_gridfs
Author: Andreas Jung
Author-email: info@zopyx.com
License: UNKNOWN
Keywords: web pyramid pylons mongodb
Platform: UNKNOWN
Classifier: Programming Language :: Python
Classifier: Framework :: Pylons
Classifier: Topic :: Internet :: WWW/HTTP
Classifier: Topic :: Internet :: WWW/HTTP :: WSGI :: Application
